.gitignore
CHANGES.txt
MANIFEST.in
README.md
README.txt
base.cfg
bootstrap.py
buildout.cfg
collective.noticeboard.sublime-project
develop.cfg
pac_buildout.cfg
setup.py
src/collective/__init__.py
src/collective.noticeboard.egg-info/PKG-INFO
src/collective.noticeboard.egg-info/SOURCES.txt
src/collective.noticeboard.egg-info/dependency_links.txt
src/collective.noticeboard.egg-info/entry_points.txt
src/collective.noticeboard.egg-info/namespace_packages.txt
src/collective.noticeboard.egg-info/not-zip-safe
src/collective.noticeboard.egg-info/requires.txt
src/collective.noticeboard.egg-info/top_level.txt
src/collective/noticeboard/__init__.py
src/collective/noticeboard/adapters.py
src/collective/noticeboard/configure.zcml
src/collective/noticeboard/events.py
src/collective/noticeboard/interfaces.py
src/collective/noticeboard/permissions.py
src/collective/noticeboard/permissions.zcml
src/collective/noticeboard/settings.py
src/collective/noticeboard/testing.py
src/collective/noticeboard/browser/__init__.py
src/collective/noticeboard/browser/configure.zcml
src/collective/noticeboard/browser/noteviews.py
src/collective/noticeboard/browser/noticeboardview.py
src/collective/noticeboard/browser/settings.py
src/collective/noticeboard/browser/templates/noticeboard.pt
src/collective/noticeboard/browser/templates/noticeboardarchive.pt
src/collective/noticeboard/locales/README.txt
src/collective/noticeboard/locales/collective.noticeboard.pot
src/collective/noticeboard/locales/de/LC_MESSAGES/collective.noticeboard.po
src/collective/noticeboard/locales/en/LC_MESSAGES/collective.noticeboard.po
src/collective/noticeboard/profiles/default/cssregistry.xml
src/collective/noticeboard/profiles/default/jsregistry.xml
src/collective/noticeboard/profiles/default/metadata.xml
src/collective/noticeboard/profiles/default/rolemap.xml
src/collective/noticeboard/profiles/default/types.xml
src/collective/noticeboard/profiles/default/types/Collection.xml
src/collective/noticeboard/profiles/default/types/Folder.xml
src/collective/noticeboard/profiles/default/types/Plone_Site.xml
src/collective/noticeboard/profiles/default/types/Topic.xml
src/collective/noticeboard/resources/handle.png
src/collective/noticeboard/resources/mustache.js
src/collective/noticeboard/resources/no.png
src/collective/noticeboard/resources/notetemplate.mustache
src/collective/noticeboard/resources/noticeboard.css
