Metadata-Version: 1.1
Name: collective.noticeboard
Version: 0.7.1
Summary: A fancy noticeboard for Plone
Home-page: http://github.com/collective/collective.noticeboard
Author: Philip Bauer
Author-email: team@starzel.de
License: gpl
Keywords: Plone javascript
Platform: UNKNOWN
Classifier: Environment :: Web Environment
Classifier: Framework :: Plone
Classifier: Framework :: Plone :: 4.2
Classifier: Framework :: Plone :: 4.3
Classifier: Framework :: Zope2
Classifier: Topic :: Communications
Classifier: Topic :: Internet :: WWW/HTTP :: Dynamic Content :: Message Boards
Classifier: License :: OSI Approved :: GNU General Public License (GPL)
Classifier: Operating System :: OS Independent
Classifier: Programming Language :: Python :: 2.6
Classifier: Programming Language :: Python :: 2.7
